{
  "auditEventIds": ["ADM-027", "ADM-049"],
  "actionButtons": [
    {
      "buttonName": {
        "eng": "Upload Data",
        "ara": "إضافة مركز",
        "fra": "Ajouter le centre",
        "hin": "डेटा अपलोड करें  ",
        "kan": "ಡೇಟಾವನ್ನು ಅಪ್‌ಲೋಡ್ ಮಾಡಿ   ",
        "tam": "தரவைப் பதிவேற்றுக  "
      },
      "imagePath": "assets/images/add-icon.png",
      "actionListType": "redirect",
      "actionURL": "",
      "redirectURL": "admin/bulkupload/masterdataupload/create",
      "showIn": "Button",
      "validations": ""
    }
  ],
  "columnsToDisplay": [
    {
      "name": "transcationId",
      "showInListView": "true",
      "label": { "eng": "Transcation ID", "ara": "مركز ", "fra": "Centre" ,
        "hin": "लेन-देन आईडी  ",
        "kan": "ವಹಿವಾಟು ID   ",
        "tam": "பரிவர்த்தனை ஐடி  "},
      "sortOrder": "3",
      "showAsLink": "",
      "linkType": "",
      "LinkURL": ""
    },
    {
      "name": "entityName",
      "showInListView": "true",
      "label": {"eng": "Table Name", "ara": "نوع المركز", "fra": "Type de centre",
        "hin": "तालिका नाम   ",
        "kan": "ಟೇಬಲ್ ಹೆಸರು ",
        "tam": " அட்டவணை பெயர்   "},
      "sortOrder": "",
      "showAsLink": "",
      "linkType": "",
      "LinkURL": ""
    },
    {
      "name": "operation",
      "showInListView": "true",
      "label": { "eng": "Operation", "ara": "حاله", "fra": "statut" ,
        "hin": "कार्यवाही    ",
        "kan": "ಕಾರ್ಯಾಚರಣೆ  ",
        "tam": " செயல்பாடு  "},
      "sortOrder": "",
      "showAsLink": "false",
      "linkType": "",
      "LinkURL": ""
    },
    {
      "name": "count",
      "showInListView": "",
      "label": {"eng": "Count","ara": "المستخدمين","fra": "Utilisateur","hin": "गिनती   ",
        "kan": "ಎಣಿಕೆ  ",
        "tam": "எண்ணிக்கை "},
      "sortOrder": "",
      "showAsLink": "",
      "linkType": "",
      "LinkURL": ""
    },
    {
      "name": "status",
      "showInListView": "",
      "label": {"eng": "Status", "ara": "الأجهزة", "fra": "Dispositifs",
        "hin": "स्थिति   ",
        "kan": "ಸ್ಥಿತಿ   ",
        "tam": "நிலை "},
      "sortOrder": "",
      "showAsLink": "",
      "linkType": "",
      "LinkURL": ""
    },
    {
      "name": "uploadedBy",
      "showInListView": "",
      "label": {"eng": "Uploaded By", "ara": "آلات", "fra": "Machines",
        "hin": "द्वारा डाली गई  ",
        "kan": "ಇವರಿಂದ ಅಪ್‌ಲೋಡ್ ಮಾಡಲಾಗಿದೆ   ",
        "tam": "பதிவேற்றியது  "},
      "sortOrder": "",
      "showAsLink": "",
      "linkType": "",
      "LinkURL": ""
    },
    {
      "name": "timeStamp",
      "showInListView": "",
      "label": {"eng": "Date Time", "ara": "هاتف مُتَكَون", "fra": "Téléphone Contact",
        "hin": "समय टिकट    ",
        "kan": "ಟೈಮ್‌ಸ್ಟ್ಯಾಂಪ್  ",
        "tam": " நேர முத்திரை  "},
      "sortOrder": "",
      "showAsLink": "",
      "linkType": "",
      "LinkURL": ""
    }
  ],
  "paginator": {
    "totalEntries": null,
    "pageSize": "10",
    "pageSizeList": [10, 20, 30, 40, 50]
  },
  "filterColumns": [
  ]
}
